CHANGES.txt
LICENSE
MANIFEST.in
README.md
setup.py
lmgtfy/__init__.py
lmgtfy/lmgtfy.py
lmgtfy/run.py
lmgtfy.egg-info/PKG-INFO
lmgtfy.egg-info/SOURCES.txt
lmgtfy.egg-info/dependency_links.txt
lmgtfy.egg-info/entry_points.txt
lmgtfy.egg-info/requires.txt
lmgtfy.egg-info/top_level.txt