Metadata-Version: 1.0
Name: lmgtfy
Version: 0.1.1
Summary: Let me Google that for you
Home-page: UNKNOWN
Author: Akash Kothawale
Author-email: io@decached.com
License: MIT
Platform: Linux
